irmet/__init__.py
irmet/auc.py
irmet/dcg.py
irmet/types.py
irmet-0.2.1.dist-info/LICENSE
irmet-0.2.1.dist-info/METADATA
irmet-0.2.1.dist-info/WHEEL
irmet-0.2.1.dist-info/top_level.txt
irmet-0.2.1.dist-info/RECORD
